tests/__init__.py
tests/test_main.py
tests/test_openinghoursparser.py
transporthours/__init__.py
transporthours/main.py
transporthours/openinghoursparser.py
transporthours-0.0.4.dist-info/LICENSE.txt
transporthours-0.0.4.dist-info/METADATA
transporthours-0.0.4.dist-info/WHEEL
transporthours-0.0.4.dist-info/top_level.txt
transporthours-0.0.4.dist-info/RECORD
