Metadata-Version: 2.1
Name: transporthours
Version: 0.0.4
Summary: Package for handling public transport routes opening hours from OpenStreetMap
Home-page: https://github.com/Jungle-Bus/transport-hours-py
Author: Adrien Pavie & Jungle Bus
Author-email: panieravide@riseup.net
License: GNU LGPLv3
Platform: UNKNOWN
Classifier: Intended Audience :: Developers
Classifier: License :: OSI Approved :: GNU Lesser General Public License v3 (LGPLv3)
Classifier: Operating System :: OS Independent
Classifier: Programming Language :: Python :: 2.7
Classifier: Topic :: Scientific/Engineering :: GIS
Classifier: Topic :: Software Development :: Libraries
Requires-Python: >=2.7
